---
title: 运行时方法区
updated: 2023-02-26T10:06:08
created: 2022-05-06T16:08:09
---

在运行时方法区中，类信息中记录了哪个ClassLoader加载了该类，同时ClassLoader也记录了它加载了哪些类

查看class文件：javap -v -p MethodInnerStrucTest.class \> test.txt 反编译字节码文件，并输出值文本文件中，便于查看。参数 -p 确保能查看 private 权限类型的字段或方法

**Classfile** /F:/IDEAWorkSpaceSourceCode/JVMDemo/out/production/chapter09/com/atguigu/java/MethodInnerStrucTest.class
Last modified 2020-11-13; size 1626 bytes
MD5 checksum 0d0fcb54854d4ce183063df985141ad0
Compiled from "MethodInnerStrucTest.java"
**//类型信息**
public class com.atguigu.java.MethodInnerStrucTest extends java.lang.Object implements java.lang.Comparable\<java.lang.String\>, java.io.Serializable
minor version: 0
major version: 52
flags: ACC_PUBLIC, ACC_SUPER
**<u>// 常量池（不是运行时常量池哦）</u>**
**Constant pool**:
\#1 = Methodref \#18.#52 // java/lang/Object."\<init\>":()V
\#2 = Fieldref \#17.#53 // com/atguigu/java/MethodInnerStrucTest.num:I
\#3 = Fieldref \#54.#55 // java/lang/System.out:Ljava/io/PrintStream;
\#4 = Class \#56 // java/lang/StringBuilder
\#5 = Methodref \#4.#52 //
…..
\#83 = Utf8 (Ljava/lang/String;)V
\#84 = Utf8 printStackTrace
{
**//域信息**
public int num;
descriptor: I
flags: ACC_PUBLIC
private static java.lang.String str;
descriptor: Ljava/lang/String;
flags: ACC_PRIVATE, ACC_STATIC

**//方法信息**
public com.atguigu.java.MethodInnerStrucTest();
descriptor: ()V
flags: ACC_PUBLIC
Code:
stack=2, locals=1, args_size=1
0: aload_0
**1: invokespecial \#1 // Method java/lang/Object."\<init\>":()V**
4: aload_0
5: bipush 10
7: putfield \#2 // Field num:I
10: return
**LineNumberTable**:
line 10: 0
line 12: 4
**LocalVariableTable**:
Start Length Slot Name Signature
0 11 0 this Lcom/atguigu/java/MethodInnerStrucTest;
public void test1();
descriptor: ()V
flags: ACC_PUBLIC
Code:
**stack=3, locals=2, args_size=1**
0: bipush 20
……
28: return
LineNumberTable:
line 17: 0
LocalVariableTable:
Start Length Slot Name Signature
0 29 0 this Lcom/atguigu/java/MethodInnerStrucTest;
static {};
descriptor: ()V
flags: ACC_STATIC
Code:
stack=1, locals=0, args_size=0
0: ldc \#15 // String 测试方法的内部结构
2: putstatic \#16 // Field str:Ljava/lang/String;
5: return
LineNumberTable:
line 13: 0
}
Signature: \#49 // Ljava/lang/Object;Ljava/lang/Comparable\<Ljava/lang/String;\>;Ljava/io/Serializable;
**SourceFile: "MethodInnerStrucTest.java"**
()V表示方法返回值类型为 void

stack=3 表示操作数栈深度为 3
locals=2 表示局部变量个数为 2 个（实例方法包含 this）
方法虽然没有参数，但是其 args_size=1 ，这时因为将 this 作为了参数

**\#15，#16等等这些带# 的，都是引用了常量池。**
